canvas_lms_mcp/__init__.py
canvas_lms_mcp/client.py
canvas_lms_mcp/main.py
canvas_lms_mcp/schema.py
canvas_lms_mcp/tools.py
canvas_lms_mcp/utils.py
canvas_lms_mcp-0.1.2.dist-info/METADATA
canvas_lms_mcp-0.1.2.dist-info/WHEEL
canvas_lms_mcp-0.1.2.dist-info/entry_points.txt
canvas_lms_mcp-0.1.2.dist-info/licenses/LICENSE
canvas_lms_mcp-0.1.2.dist-info/RECORD
