Metadata-Version: 2.4
Name: canvas-lms-mcp
Version: 0.1.2
Summary: Minimal Canvas LMS MCP server for easy access to education
Project-URL: Homepage, https://github.com/ahnopologetic/canvas-lms-mcp
Project-URL: Bug Tracker, https://github.com/ahnopologetic/canvas-lms-mcp/issues
Project-URL: Documentation, https://github.com/ahnopologetic/canvas-lms-mcp#readme
Author-email: Humphrey Ahn <stahn1995@gmail.com>
License: MIT
License-File: LICENSE
Classifier: License :: OSI Approved :: MIT License
Classifier: Operating System :: OS Independent
Classifier: Programming Language :: Python :: 3
Classifier: Programming Language :: Python :: 3.10
Classifier: Programming Language :: Python :: 3.11
Classifier: Programming Language :: Python :: 3.12
Classifier: Programming Language :: Python :: 3.13
Classifier: Topic :: Education
Classifier: Topic :: Internet :: WWW/HTTP :: HTTP Servers
Requires-Python: >=3.10
Requires-Dist: fastapi>=0.68.0
Requires-Dist: fastmcp>=2.1.0
Requires-Dist: httpx>=0.24.0
Requires-Dist: pydantic>=2.0.0
Requires-Dist: uvicorn>=0.15.0
Provides-Extra: dev
Requires-Dist: black>=23.0.0; extra == 'dev'
Requires-Dist: mypy>=1.0.0; extra == 'dev'
Requires-Dist: pytest-asyncio>=0.18.0; extra == 'dev'
Requires-Dist: pytest-cov>=4.0.0; extra == 'dev'
Requires-Dist: pytest>=7.0.0; extra == 'dev'
Requires-Dist: ruff>=0.0.40; extra == 'dev'
